[
    {
      "id": "Fs3sC73B3jCsrFgw",
      "author": "Jenny",
      "business": "SxQaqIGwTRsuPnGT",
      "text": "This place is amazing, best Italian in Columbia",
      "rating": 4.9
    },
    {
      "id": "PwKBvehj87UUBNmO",
      "author": "Ben",
      "business": "ySwgsMAaAB30AdKd",
      "text": "This place is very sophisticated and pleasent",
      "rating": 3.6
    },
    {
      "id": "glke9YjT4Bxmk32o",
      "author": "Jen",
      "business": "ySwgsMAaAB30AdKd",
      "text": "There is good culture working here",
      "rating": 3.8
    },
    {
      "id": "vRl0NWzAFg1lhFmZ",
      "author": "Fred",
      "business": "KRz1j0Gl67bzSomK",
      "text": "Such a great place",
      "rating": 3.2
    },
    {
      "id": "Z1k6GN9QLBUEncr0",
      "author": "Betsy",
      "business": "w9OJ0bsIAHC0FVD8",
      "text": "Great Serivce, Fantastic Staff",
      "rating": 4
    },
    {
      "id": "BPQyeCBGYYP5Gi8f",
      "author": "Daphne",
      "business": "w9OJ0bsIAHC0FVD8",
      "text": "Had a great experience, but stains in car",
      "rating": 3.8
    },
    {
      "id": "M7oKDOpre77pLlvq",
      "author": "Chris",
      "business": "bYtDlJ5FeRtH49UK",
      "text": "Great Coaches, Fantastic service",
      "rating": 3.8
    },
    {
      "id": "a12c3547-1256-462e-9ca4-fa31c4f363f6",
      "author": "adrian",
      "business": "SxQaqIGwTRsuPnGT",
      "text": "",
      "rating": 3.2
    },
    {
      "id": "f42bda59-4d84-4a1a-aa2b-96a44d6955b5",
      "author": "Jon",
      "business": "SxQaqIGwTRsuPnGT",
      "text": "This is a test review, please ignore",
      "rating": 3.2
    },
    {
      "id": "9b3a8877-d3ab-4851-a3c7-9a7ceae8e5d5",
      "author": "test",
      "business": "SxQaqIGwTRsuPnGT",
      "text": "test",
      "rating": 3.2
    },
    {
      "id": "2b73fbef-a427-4e27-9cb5-df875f397e97",
      "author": "",
      "business": "SxQaqIGwTRsuPnGT",
      "text": "",
      "rating": 0
    },
    {
      "id": "fed4dc35-342e-410e-a92e-fc91bde6d928",
      "author": "Adrian",
      "business": "LKm8gjX0Hbb961fS",
      "text": "This is test",
      "rating": 3
    },
    {
      "id": "b97c86e3-3230-476b-a221-7e2e52d4b0e4",
      "author": "Tester",
      "business": "ySwgsMAaAB30AdKd",
      "text": "This is testefdfsdfsdfsd",
      "rating": 3.2
    }
]